{
    "time": "2024-10-07 20:47:06",
    "itemsCount": 50,
    "itemsList": [
        {
            "gun_name": "USP-S",
            "skin_name": "Blueprint",
            "state": "Field-Tested",
            "priceRub": 1061.33
        },
        {
            "gun_name": "P90",
            "skin_name": "Verdant Growth",
            "state": "Factory New",
            "priceRub": 1029.55
        },
        {
            "gun_name": "Sticker",
            "skin_name": "BIG (Holo) | Stockholm 2021",
            "state": "",
            "priceRub": 1019.95
        },
        {
            "gun_name": "Sticker",
            "skin_name": "Cloud9 (Holo) | Rio 2022",
            "state": "",
            "priceRub": 994.35
        },
        {
            "gun_name": "USP-S",
            "skin_name": "Cortex",
            "state": "Minimal Wear",
            "priceRub": 990.93
        },
        {
            "gun_name": "Sticker",
            "skin_name": "Loving Eyes",
            "state": "Holo",
            "priceRub": 964.69
        },
        {
            "gun_name": "MP5-SD",
            "skin_name": "Phosphor",
            "state": "Field-Tested",
            "priceRub": 961.71
        },
        {
            "gun_name": "Sticker",
            "skin_name": "hades (Gold) | Paris 2023",
            "state": "",
            "priceRub": 961.49
        },
        {
            "gun_name": "FAMAS",
            "skin_name": "CaliCamo",
            "state": "Battle-Scarred",
            "priceRub": 960.64
        },
        {
            "gun_name": "Sticker",
            "skin_name": "Hobbit (Holo) | Antwerp 2022",
            "state": "",
            "priceRub": 942.93
        },
        {
            "gun_name": "Souvenir Package",
            "skin_name": "Stockholm 2021 Vertigo",
            "state": "",
            "priceRub": 934.19
        },
        {
            "gun_name": "P90",
            "skin_name": "Storm",
            "state": "Minimal Wear",
            "priceRub": 917.76
        },
        {
            "gun_name": "Galil AR",
            "skin_name": "Crimson Tsunami",
            "state": "Factory New",
            "priceRub": 912.43
        },
        {
            "gun_name": "MAG-7",
            "skin_name": "Irradiated Alert",
            "state": "Well-Worn",
            "priceRub": 900.69
        },
        {
            "gun_name": "P2000",
            "skin_name": "Handgun",
            "state": "Factory New",
            "priceRub": 888.53
        },
        {
            "gun_name": "Dual Berettas",
            "skin_name": "Briar",
            "state": "Minimal Wear",
            "priceRub": 882.77
        },
        {
            "gun_name": "Sticker",
            "skin_name": "isak (Holo) | Paris 2023",
            "state": "",
            "priceRub": 874.03
        },
        {
            "gun_name": "Sticker",
            "skin_name": "JT (Holo) | Paris 2023",
            "state": "",
            "priceRub": 863.36
        },
        {
            "gun_name": "Sticker",
            "skin_name": "JACKZ (Holo) | Stockholm 2021",
            "state": "",
            "priceRub": 863.36
        },
        {
            "gun_name": "Sticker",
            "skin_name": "Team Liquid (Foil) | Stockholm 2021",
            "state": "",
            "priceRub": 854.61
        },
        {
            "gun_name": "Sticker",
            "skin_name": "KSCERATO (Holo) | Stockholm 2021",
            "state": "",
            "priceRub": 842.45
        },
        {
            "gun_name": "Tec-9",
            "skin_name": "Bamboo Forest",
            "state": "Field-Tested",
            "priceRub": 836.05
        },
        {
            "gun_name": "Sticker",
            "skin_name": "Gambit Gaming (Foil) | Stockholm 2021",
            "state": "",
            "priceRub": 835.41
        },
        {
            "gun_name": "Sticker",
            "skin_name": "Complexity Gaming (Gold) | Antwerp 2022",
            "state": "",
            "priceRub": 828.16
        },
        {
            "gun_name": "Sticker",
            "skin_name": "jabbi (Holo) | Rio 2022",
            "state": "",
            "priceRub": 824.53
        },
        {
            "gun_name": "P90",
            "skin_name": "Storm",
            "state": "Field-Tested",
            "priceRub": 824.32
        },
        {
            "gun_name": "MP7",
            "skin_name": "Vault Heist",
            "state": "Field-Tested",
            "priceRub": 821.33
        },
        {
            "gun_name": "Sticker",
            "skin_name": "G2 Esports (Holo) | Antwerp 2022",
            "state": "",
            "priceRub": 812.59
        },
        {
            "gun_name": "G3SG1",
            "skin_name": "The Executioner",
            "state": "Battle-Scarred",
            "priceRub": 810.45
        },
        {
            "gun_name": "Sticker",
            "skin_name": "GODSENT (Holo) | Stockholm 2021",
            "state": "",
            "priceRub": 807.89
        },
        {
            "gun_name": "Sticker",
            "skin_name": "saffee (Holo) | Paris 2023",
            "state": "",
            "priceRub": 807.47
        },
        {
            "gun_name": "MP9",
            "skin_name": "Starlight Protector",
            "state": "Field-Tested",
            "priceRub": 803.63
        },
        {
            "gun_name": "Sticker",
            "skin_name": "Goofy (Gold) | Paris 2023",
            "state": "",
            "priceRub": 797.23
        },
        {
            "gun_name": "MAC-10",
            "skin_name": "Malachite",
            "state": "Factory New",
            "priceRub": 791.89
        },
        {
            "gun_name": "Galil AR",
            "skin_name": "Stone Cold",
            "state": "Minimal Wear",
            "priceRub": 786.35
        },
        {
            "gun_name": "XM1014",
            "skin_name": "Red Python",
            "state": "Minimal Wear",
            "priceRub": 778.45
        },
        {
            "gun_name": "MP7",
            "skin_name": "Vault Heist",
            "state": "Battle-Scarred",
            "priceRub": 778.45
        },
        {
            "gun_name": "Sticker",
            "skin_name": "KEi (Gold) | Paris 2023",
            "state": "",
            "priceRub": 770.56
        },
        {
            "gun_name": "M4A4",
            "skin_name": "Tooth Fairy",
            "state": "Field-Tested",
            "priceRub": 769.71
        },
        {
            "gun_name": "P250",
            "skin_name": "Visions",
            "state": "Field-Tested",
            "priceRub": 759.89
        },
        {
            "gun_name": "Sticker",
            "skin_name": "Boom",
            "state": "Foil",
            "priceRub": 756.05
        },
        {
            "gun_name": "Sticker",
            "skin_name": "G2 Esports (Holo) | Stockholm 2021",
            "state": "",
            "priceRub": 754.13
        },
        {
            "gun_name": "MAC-10",
            "skin_name": "Heat",
            "state": "Battle-Scarred",
            "priceRub": 752.0
        },
        {
            "gun_name": "FAMAS",
            "skin_name": "Macabre",
            "state": "Field-Tested",
            "priceRub": 751.15
        },
        {
            "gun_name": "MP7",
            "skin_name": "Abyssal Apparition",
            "state": "Minimal Wear",
            "priceRub": 748.16
        },
        {
            "gun_name": "Sticker",
            "skin_name": "HooXi (Holo) | Paris 2023",
            "state": "",
            "priceRub": 741.12
        },
        {
            "gun_name": "P250",
            "skin_name": "Asiimov",
            "state": "Field-Tested",
            "priceRub": 740.48
        },
        {
            "gun_name": "USP-S",
            "skin_name": "Cyrex",
            "state": "Factory New",
            "priceRub": 740.48
        },
        {
            "gun_name": "Glock-18",
            "skin_name": "Vogue",
            "state": "Field-Tested",
            "priceRub": 737.71
        },
        {
            "gun_name": "Five-SeveN",
            "skin_name": "Contractor",
            "state": "Minimal Wear",
            "priceRub": 735.57
        }
    ]
}